hip_python_as_cuda/__init__.py
test_hip_python_as_cuda-0.0.1.dist-info/METADATA
test_hip_python_as_cuda-0.0.1.dist-info/WHEEL
test_hip_python_as_cuda-0.0.1.dist-info/top_level.txt
test_hip_python_as_cuda-0.0.1.dist-info/RECORD
