Metadata-Version: 2.4
Name: test-hip-python-as-cuda
Version: 0.0.1
Summary: Use HIP Python via CUDA names
Author-email: AMD <support@amd.com>
License: MIT
Project-URL: Homepage, https://github.com/ROCmSoftwarePlatform/hip-python
Requires-Python: >=3.8
